{
  "schema_version": 2,
  "tests": {
    "ags-aging-full": {
      "hle": {
        "canonical_pass_hash": "cac70be3cfa28ebac5515a72319f34a8ce61aba6ae825d65d8c8de85bc5e3673",
        "canonical_pass_screenshot": "verified/ags-aging-full-hle-nba.bmp",
        "canonical_pass_verified_by": "auto-consensus-2 2026-04-07",
        "canonical_pass_verified_at": "2026-04-07T01:08:32.591391+00:00",
        "canonical_pass_notes": "Re-promoted from 2-runner consensus; previous canonical was 28f46991896a85c8.",
        "runners": {
          "cable_club": {
            "hash": "ba847b3c2db08b5b3047bf1049ca9655d6081ca73f5d9677cda2237b93f02ff3",
            "screenshot": "verified/ags-aging-full-hle-cable_club.bmp",
            "status": "bug",
            "verified_by": "chris",
            "verified_at": "2026-04-07T01:08:32.591391+00:00",
            "frames": 3000,
            "notes": "2026-04-07 post commits c93d87c + edff1f3"
          },
          "mgba": {
            "hash": "cac70be3cfa28ebac5515a72319f34a8ce61aba6ae825d65d8c8de85bc5e3673",
            "screenshot": "verified/ags-aging-full-hle-mgba.bmp",
            "status": "bug",
            "verified_by": "chris",
            "verified_at": "2026-04-07T01:08:32.591391+00:00",
            "frames": 3000,
            "notes": "Stuck on AGS 'LOAD CONFIGURATION / CHECK SUM ERROR / DEFAULT IS SAVED' screen. AGS is trying to load saved configuration data and the runner doesn't provide a save file, so AGS shows the checksum error and never advances past the loader to actually run the tests. Bit-identical hash between mgba and skyemu - same shared failure mode. NOT a bug in either emulator strictly speaking; it's a runner-side test setup issue (we should provide AGS with a save file to skip the config loader). Filed as part of task #11 (test setup needs work)."
          },
          "nanoboyadvance": {
            "hash": "28f46991896a85c80d9aba2205421a27fb52f9edab28af42697f866e5d04ecbb",
            "screenshot": "verified/ags-aging-full-hle-nba.bmp",
            "status": "pass",
            "verified_by": "chris",
            "verified_at": "2026-04-07T01:08:32.591391+00:00",
            "frames": 3000,
            "notes": "LONE PASSER under HLE. NBA actually executes the AGS test suite to the results page: MEMORY PASS, LCD PASS, TIMER PASS, DMA PASS, COM N/A (requires link cable hardware), KEY INPUT PASS, INTERRUPT PASS. 6 of 7 sections pass on a single emulator instance."
          },
          "skyemu": {
            "hash": "cac70be3cfa28ebac5515a72319f34a8ce61aba6ae825d65d8c8de85bc5e3673",
            "screenshot": "verified/ags-aging-full-hle-skyemu.bmp",
            "status": "bug",
            "verified_by": "chris",
            "verified_at": "2026-04-07T01:08:32.591391+00:00",
            "frames": 3000,
            "notes": "Stuck on AGS 'LOAD CONFIGURATION / CHECK SUM ERROR / DEFAULT IS SAVED' screen. AGS is trying to load saved configuration data and the runner doesn't provide a save file, so AGS shows the checksum error and never advances past the loader to actually run the tests. Bit-identical hash between mgba and skyemu - same shared failure mode. NOT a bug in either emulator strictly speaking; it's a runner-side test setup issue (we should provide AGS with a save file to skip the config loader). Filed as part of task #11 (test setup needs work)."
          }
        }
      },
      "official": {
        "canonical_pass_hash": "cac70be3cfa28ebac5515a72319f34a8ce61aba6ae825d65d8c8de85bc5e3673",
        "canonical_pass_screenshot": "verified/ags-aging-full-official-nba.bmp",
        "canonical_pass_verified_by": "auto-consensus-2 2026-04-07",
        "canonical_pass_verified_at": "2026-04-07T01:08:32.591391+00:00",
        "canonical_pass_notes": "Re-promoted from 2-runner consensus; previous canonical was 5912c0bd89f9b06e.",
        "runners": {
          "cable_club": {
            "hash": "ba847b3c2db08b5b3047bf1049ca9655d6081ca73f5d9677cda2237b93f02ff3",
            "screenshot": "verified/ags-aging-full-official-cable_club.bmp",
            "status": "bug",
            "verified_by": "chris",
            "verified_at": "2026-04-07T01:08:32.591391+00:00",
            "frames": 3000,
            "notes": "2026-04-07 post commits c93d87c + edff1f3"
          },
          "mgba": {
            "hash": "cac70be3cfa28ebac5515a72319f34a8ce61aba6ae825d65d8c8de85bc5e3673",
            "screenshot": "verified/ags-aging-full-official-mgba.bmp",
            "status": "bug",
            "verified_by": "chris",
            "verified_at": "2026-04-07T01:08:32.591391+00:00",
            "frames": 3000,
            "notes": "Stuck on AGS 'LOAD CONFIGURATION / CHECK SUM ERROR / DEFAULT IS SAVED' screen. AGS is trying to load saved configuration data and the runner doesn't provide a save file, so AGS shows the checksum error and never advances past the loader to actually run the tests. Bit-identical hash between mgba and skyemu - same shared failure mode. NOT a bug in either emulator strictly speaking; it's a runner-side test setup issue (we should provide AGS with a save file to skip the config loader). Filed as part of task #11 (test setup needs work)."
          },
          "nanoboyadvance": {
            "hash": "5912c0bd89f9b06e34af60326d09332fde0bdbadedb3382022cff2836d0666f4",
            "screenshot": "verified/ags-aging-full-official-nba.bmp",
            "status": "pass",
            "verified_by": "chris",
            "verified_at": "2026-04-07T01:08:32.591391+00:00",
            "frames": 3000,
            "notes": "LONE PASSER under official BIOS. Same test result page as HLE plus an extra 'PUSH START TO AGING' prompt at the bottom (the gateway to the extended aging loop, which requires interactive input to enter). All 6 testable sections show PASS."
          },
          "skyemu": {
            "hash": "cac70be3cfa28ebac5515a72319f34a8ce61aba6ae825d65d8c8de85bc5e3673",
            "screenshot": "verified/ags-aging-full-official-skyemu.bmp",
            "status": "bug",
            "verified_by": "chris",
            "verified_at": "2026-04-07T01:08:32.591391+00:00",
            "frames": 3000,
            "notes": "Stuck on AGS 'LOAD CONFIGURATION / CHECK SUM ERROR / DEFAULT IS SAVED' screen. AGS is trying to load saved configuration data and the runner doesn't provide a save file, so AGS shows the checksum error and never advances past the loader to actually run the tests. Bit-identical hash between mgba and skyemu - same shared failure mode. NOT a bug in either emulator strictly speaking; it's a runner-side test setup issue (we should provide AGS with a save file to skip the config loader). Filed as part of task #11 (test setup needs work)."
          }
        }
      },
      "cleanroom": {
        "canonical_pass_hash": "cac70be3cfa28ebac5515a72319f34a8ce61aba6ae825d65d8c8de85bc5e3673",
        "canonical_pass_screenshot": "verified/ags-aging-full-cleanroom-nba.bmp",
        "canonical_pass_verified_by": "auto-consensus-2 2026-04-07",
        "canonical_pass_verified_at": "2026-04-07T01:08:32.591391+00:00",
        "canonical_pass_notes": "Re-promoted from 2-runner consensus; previous canonical was 28f46991896a85c8.",
        "runners": {
          "cable_club": {
            "hash": "ba847b3c2db08b5b3047bf1049ca9655d6081ca73f5d9677cda2237b93f02ff3",
            "screenshot": "verified/ags-aging-full-cleanroom-cable_club.bmp",
            "status": "bug",
            "verified_by": "chris",
            "verified_at": "2026-04-07T01:08:32.591391+00:00",
            "frames": 3000,
            "notes": "2026-04-07 post commits c93d87c + edff1f3"
          },
          "mgba": {
            "hash": "cac70be3cfa28ebac5515a72319f34a8ce61aba6ae825d65d8c8de85bc5e3673",
            "screenshot": "verified/ags-aging-full-cleanroom-mgba.bmp",
            "status": "bug",
            "verified_by": "chris",
            "verified_at": "2026-04-07T01:08:32.591391+00:00",
            "frames": 3000,
            "notes": "Stuck on AGS 'LOAD CONFIGURATION / CHECK SUM ERROR / DEFAULT IS SAVED' screen. AGS is trying to load saved configuration data and the runner doesn't provide a save file, so AGS shows the checksum error and never advances past the loader to actually run the tests. Bit-identical hash between mgba and skyemu - same shared failure mode. NOT a bug in either emulator strictly speaking; it's a runner-side test setup issue (we should provide AGS with a save file to skip the config loader). Filed as part of task #11 (test setup needs work)."
          },
          "nanoboyadvance": {
            "hash": "28f46991896a85c80d9aba2205421a27fb52f9edab28af42697f866e5d04ecbb",
            "screenshot": "verified/ags-aging-full-cleanroom-nba.bmp",
            "status": "pass",
            "verified_by": "chris",
            "verified_at": "2026-04-07T01:08:32.591391+00:00",
            "frames": 3000,
            "notes": "Same hash as HLE - NBA's HLE and cleanroom modes differ only in which BIOS file is loaded, and AGS doesn't exercise BIOS paths differently between them."
          },
          "skyemu": {
            "hash": "cac70be3cfa28ebac5515a72319f34a8ce61aba6ae825d65d8c8de85bc5e3673",
            "screenshot": "verified/ags-aging-full-cleanroom-skyemu.bmp",
            "status": "bug",
            "verified_by": "chris",
            "verified_at": "2026-04-07T01:08:32.591391+00:00",
            "frames": 3000,
            "notes": "Stuck on AGS 'LOAD CONFIGURATION / CHECK SUM ERROR / DEFAULT IS SAVED' screen. AGS is trying to load saved configuration data and the runner doesn't provide a save file, so AGS shows the checksum error and never advances past the loader to actually run the tests. Bit-identical hash between mgba and skyemu - same shared failure mode. NOT a bug in either emulator strictly speaking; it's a runner-side test setup issue (we should provide AGS with a save file to skip the config loader). Filed as part of task #11 (test setup needs work)."
          }
        }
      }
    }
  }
}