{
  "schema_version": 2,
  "tests": {
    "ags-aging-full": {
      "hle": {
        "canonical_pass_hash": "28f46991896a85c80d9aba2205421a27fb52f9edab28af42697f866e5d04ecbb",
        "canonical_pass_screenshot": "verified/ags-aging-full-hle-nba.bmp",
        "canonical_pass_verified_by": "chris",
        "canonical_pass_verified_at": "2026-04-07T01:08:32.591391+00:00",
        "canonical_pass_notes": "AGS Aging Cartridge results page showing MEMORY/LCD/TIMER/DMA/KEY INPUT/INTERRUPT all PASS, COM N/A. NBA is the LONE PASSER across all 4 runners - mgba and skyemu are stuck on AGS save-loader checksum screen, cable_club is stuck even earlier. The verification arc surfaced this as a major divergence and demonstrates why consensus-based scoring is wrong: mgba+skyemu agreement on the loader-error screen would have been recorded as 'gold' under the old scheme, masking the fact that they don't actually run the test suite at all.",
        "runners": {
          "cable_club": {
            "hash": "e2cc2a1fa6131cf4d86faa3baf78851f35a36853e2467c257b3df9d89e85cce5",
            "screenshot": "verified/ags-aging-full-hle-cable_club.bmp",
            "status": "bug",
            "verified_by": "chris",
            "verified_at": "2026-04-07T01:08:32.591391+00:00",
            "frames": 3000,
            "notes": "Cable Club fails to run AGS - captures pure black screen. cable_club never reaches the AGS title or save-loader. Third real cable_club bug found by verification arc. See task #12."
          },
          "mgba": {
            "hash": "cac70be3cfa28ebac5515a72319f34a8ce61aba6ae825d65d8c8de85bc5e3673",
            "screenshot": "verified/ags-aging-full-hle-mgba.bmp",
            "status": "bug",
            "verified_by": "chris",
            "verified_at": "2026-04-07T01:08:32.591391+00:00",
            "frames": 3000,
            "notes": "Stuck on AGS 'LOAD CONFIGURATION / CHECK SUM ERROR / DEFAULT IS SAVED' screen. AGS is trying to load saved configuration data and the runner doesn't provide a save file, so AGS shows the checksum error and never advances past the loader to actually run the tests. Bit-identical hash between mgba and skyemu - same shared failure mode. NOT a bug in either emulator strictly speaking; it's a runner-side test setup issue (we should provide AGS with a save file to skip the config loader). Filed as part of task #11 (test setup needs work)."
          },
          "nanoboyadvance": {
            "hash": "28f46991896a85c80d9aba2205421a27fb52f9edab28af42697f866e5d04ecbb",
            "screenshot": "verified/ags-aging-full-hle-nba.bmp",
            "status": "pass",
            "verified_by": "chris",
            "verified_at": "2026-04-07T01:08:32.591391+00:00",
            "frames": 3000,
            "notes": "LONE PASSER under HLE. NBA actually executes the AGS test suite to the results page: MEMORY PASS, LCD PASS, TIMER PASS, DMA PASS, COM N/A (requires link cable hardware), KEY INPUT PASS, INTERRUPT PASS. 6 of 7 sections pass on a single emulator instance."
          },
          "skyemu": {
            "hash": "cac70be3cfa28ebac5515a72319f34a8ce61aba6ae825d65d8c8de85bc5e3673",
            "screenshot": "verified/ags-aging-full-hle-skyemu.bmp",
            "status": "bug",
            "verified_by": "chris",
            "verified_at": "2026-04-07T01:08:32.591391+00:00",
            "frames": 3000,
            "notes": "Stuck on AGS 'LOAD CONFIGURATION / CHECK SUM ERROR / DEFAULT IS SAVED' screen. AGS is trying to load saved configuration data and the runner doesn't provide a save file, so AGS shows the checksum error and never advances past the loader to actually run the tests. Bit-identical hash between mgba and skyemu - same shared failure mode. NOT a bug in either emulator strictly speaking; it's a runner-side test setup issue (we should provide AGS with a save file to skip the config loader). Filed as part of task #11 (test setup needs work)."
          }
        }
      },
      "official": {
        "canonical_pass_hash": "5912c0bd89f9b06e34af60326d09332fde0bdbadedb3382022cff2836d0666f4",
        "canonical_pass_screenshot": "verified/ags-aging-full-official-nba.bmp",
        "canonical_pass_verified_by": "chris",
        "canonical_pass_verified_at": "2026-04-07T01:08:32.591391+00:00",
        "canonical_pass_notes": "AGS Aging Cartridge results page showing MEMORY/LCD/TIMER/DMA/KEY INPUT/INTERRUPT all PASS, COM N/A. NBA is the LONE PASSER across all 4 runners - mgba and skyemu are stuck on AGS save-loader checksum screen, cable_club is stuck even earlier. The verification arc surfaced this as a major divergence and demonstrates why consensus-based scoring is wrong: mgba+skyemu agreement on the loader-error screen would have been recorded as 'gold' under the old scheme, masking the fact that they don't actually run the test suite at all.",
        "runners": {
          "cable_club": {
            "hash": "96f750d8f4dff67d105322f6f2b5b3f36919a18982cd17ca3270d4ca98ba8e35",
            "screenshot": "verified/ags-aging-full-official-cable_club.bmp",
            "status": "bug",
            "verified_by": "chris",
            "verified_at": "2026-04-07T01:08:32.591391+00:00",
            "frames": 3000,
            "notes": "Cable Club captures pure white screen under official BIOS (different broken state from HLE pure-black, but still not running AGS). Same root cause: cable_club doesn't get past the AGS bootloader."
          },
          "mgba": {
            "hash": "cac70be3cfa28ebac5515a72319f34a8ce61aba6ae825d65d8c8de85bc5e3673",
            "screenshot": "verified/ags-aging-full-official-mgba.bmp",
            "status": "bug",
            "verified_by": "chris",
            "verified_at": "2026-04-07T01:08:32.591391+00:00",
            "frames": 3000,
            "notes": "Stuck on AGS 'LOAD CONFIGURATION / CHECK SUM ERROR / DEFAULT IS SAVED' screen. AGS is trying to load saved configuration data and the runner doesn't provide a save file, so AGS shows the checksum error and never advances past the loader to actually run the tests. Bit-identical hash between mgba and skyemu - same shared failure mode. NOT a bug in either emulator strictly speaking; it's a runner-side test setup issue (we should provide AGS with a save file to skip the config loader). Filed as part of task #11 (test setup needs work)."
          },
          "nanoboyadvance": {
            "hash": "5912c0bd89f9b06e34af60326d09332fde0bdbadedb3382022cff2836d0666f4",
            "screenshot": "verified/ags-aging-full-official-nba.bmp",
            "status": "pass",
            "verified_by": "chris",
            "verified_at": "2026-04-07T01:08:32.591391+00:00",
            "frames": 3000,
            "notes": "LONE PASSER under official BIOS. Same test result page as HLE plus an extra 'PUSH START TO AGING' prompt at the bottom (the gateway to the extended aging loop, which requires interactive input to enter). All 6 testable sections show PASS."
          },
          "skyemu": {
            "hash": "cac70be3cfa28ebac5515a72319f34a8ce61aba6ae825d65d8c8de85bc5e3673",
            "screenshot": "verified/ags-aging-full-official-skyemu.bmp",
            "status": "bug",
            "verified_by": "chris",
            "verified_at": "2026-04-07T01:08:32.591391+00:00",
            "frames": 3000,
            "notes": "Stuck on AGS 'LOAD CONFIGURATION / CHECK SUM ERROR / DEFAULT IS SAVED' screen. AGS is trying to load saved configuration data and the runner doesn't provide a save file, so AGS shows the checksum error and never advances past the loader to actually run the tests. Bit-identical hash between mgba and skyemu - same shared failure mode. NOT a bug in either emulator strictly speaking; it's a runner-side test setup issue (we should provide AGS with a save file to skip the config loader). Filed as part of task #11 (test setup needs work)."
          }
        }
      },
      "cleanroom": {
        "canonical_pass_hash": "28f46991896a85c80d9aba2205421a27fb52f9edab28af42697f866e5d04ecbb",
        "canonical_pass_screenshot": "verified/ags-aging-full-cleanroom-nba.bmp",
        "canonical_pass_verified_by": "chris",
        "canonical_pass_verified_at": "2026-04-07T01:08:32.591391+00:00",
        "canonical_pass_notes": "AGS Aging Cartridge results page showing MEMORY/LCD/TIMER/DMA/KEY INPUT/INTERRUPT all PASS, COM N/A. NBA is the LONE PASSER across all 4 runners - mgba and skyemu are stuck on AGS save-loader checksum screen, cable_club is stuck even earlier. The verification arc surfaced this as a major divergence and demonstrates why consensus-based scoring is wrong: mgba+skyemu agreement on the loader-error screen would have been recorded as 'gold' under the old scheme, masking the fact that they don't actually run the test suite at all.",
        "runners": {
          "cable_club": {
            "hash": "22de4108c65c968167f7077cf6e9766b4f6a4f13c02cffb3e24845718dcae3ae",
            "screenshot": "verified/ags-aging-full-cleanroom-cable_club.bmp",
            "status": "bug",
            "verified_by": "chris",
            "verified_at": "2026-04-07T01:08:32.591391+00:00",
            "frames": 3000,
            "notes": "Cable Club cleanroom mode is broken - bit-identical 22de4108... hash to all other cleanroom captures. Stuck on Cult-of-GBA boot screen. See task #10."
          },
          "mgba": {
            "hash": "cac70be3cfa28ebac5515a72319f34a8ce61aba6ae825d65d8c8de85bc5e3673",
            "screenshot": "verified/ags-aging-full-cleanroom-mgba.bmp",
            "status": "bug",
            "verified_by": "chris",
            "verified_at": "2026-04-07T01:08:32.591391+00:00",
            "frames": 3000,
            "notes": "Stuck on AGS 'LOAD CONFIGURATION / CHECK SUM ERROR / DEFAULT IS SAVED' screen. AGS is trying to load saved configuration data and the runner doesn't provide a save file, so AGS shows the checksum error and never advances past the loader to actually run the tests. Bit-identical hash between mgba and skyemu - same shared failure mode. NOT a bug in either emulator strictly speaking; it's a runner-side test setup issue (we should provide AGS with a save file to skip the config loader). Filed as part of task #11 (test setup needs work)."
          },
          "nanoboyadvance": {
            "hash": "28f46991896a85c80d9aba2205421a27fb52f9edab28af42697f866e5d04ecbb",
            "screenshot": "verified/ags-aging-full-cleanroom-nba.bmp",
            "status": "pass",
            "verified_by": "chris",
            "verified_at": "2026-04-07T01:08:32.591391+00:00",
            "frames": 3000,
            "notes": "Same hash as HLE - NBA's HLE and cleanroom modes differ only in which BIOS file is loaded, and AGS doesn't exercise BIOS paths differently between them."
          },
          "skyemu": {
            "hash": "cac70be3cfa28ebac5515a72319f34a8ce61aba6ae825d65d8c8de85bc5e3673",
            "screenshot": "verified/ags-aging-full-cleanroom-skyemu.bmp",
            "status": "bug",
            "verified_by": "chris",
            "verified_at": "2026-04-07T01:08:32.591391+00:00",
            "frames": 3000,
            "notes": "Stuck on AGS 'LOAD CONFIGURATION / CHECK SUM ERROR / DEFAULT IS SAVED' screen. AGS is trying to load saved configuration data and the runner doesn't provide a save file, so AGS shows the checksum error and never advances past the loader to actually run the tests. Bit-identical hash between mgba and skyemu - same shared failure mode. NOT a bug in either emulator strictly speaking; it's a runner-side test setup issue (we should provide AGS with a save file to skip the config loader). Filed as part of task #11 (test setup needs work)."
          }
        }
      }
    }
  }
}